{
	  "pages": [
	    {
	      "path": "pages/index/index"
	    },
	    {
	      "path": "pages/data/index"
	    },
	    {
	      "path": "pages/profile/index"
	    },
		{
		  "path": "pages/Communication/index"
		}
	  ],
	  "tabBar": {
	    "color": "#8e8e93",
	    "selectedColor": "#007aff",
	    "backgroundColor": "#ffffff",
	    "borderStyle": "black",
	    "list": [
	      {
	        "pagePath": "pages/index/index",
	        "text": "首页",
	        "iconPath": "static/icons/home.png",
	        "selectedIconPath": "static/icons/home-active.png"
	      },
	      {
	        "pagePath": "pages/data/index",
	        "text": "数据监控",
	        "iconPath": "static/icons/data.png",
	        "selectedIconPath": "static/icons/data-active.png"
	      },
	      {
	        "pagePath": "pages/profile/index",
	        "text": "个人中心",
	        "iconPath": "static/icons/person.png",
	        "selectedIconPath": "static/icons/person-active.png"
	      }
	    ]
	  },
	"globalStyle": {
		"navigationBarTextStyle": "black",
		"navigationBarTitleText": "量子智能",
		"navigationBarBackgroundColor": "#F8F8F8",
		"backgroundColor": "#F8F8F8"
	},
	"uniIdRouter": {}
}
